setup.py
spicecmp/__init__.py
spicecmp/benches.py
spicecmp/compare_me.py
spicecmp/compare_meas.py
spicecmp/corner.py
spicecmp/errormode.py
spicecmp/mos.py
spicecmp/pdk.py
spicecmp/pdk_sim_combo.py
spicecmp/simulator.py
spicecmp/testcase.py
spicecmp.egg-info/PKG-INFO
spicecmp.egg-info/SOURCES.txt
spicecmp.egg-info/dependency_links.txt
spicecmp.egg-info/requires.txt
spicecmp.egg-info/top_level.txt
tests/__init__.py
tests/test_spicecmp.py