Metadata-Version: 2.1
Name: spicecmp
Version: 3.0
Summary: Spice Models and Results Comparisons
Home-page: https://github.com/Vlsir/Vlsir
Author: Dan Fritchman
Author-email: dan@fritch.mn
Requires-Python: >=3.8, <4
Provides-Extra: dev
